hojichar/__init__.py
hojichar/cli.py
hojichar/py.typed
hojichar/async_filters/__init__.py
hojichar/async_filters/openai.py
hojichar/core/__init__.py
hojichar/core/async_composition.py
hojichar/core/async_filter_interface.py
hojichar/core/composition.py
hojichar/core/filter_interface.py
hojichar/core/inspection.py
hojichar/core/models.py
hojichar/core/parallel.py
hojichar/dict/__init__.py
hojichar/dict/adult_keywords_en.txt
hojichar/dict/adult_keywords_ja.txt
hojichar/dict/advertisement_keywords_ja.txt
hojichar/dict/discrimination_keywords_ja.txt
hojichar/dict/dummy_ng_words.txt
hojichar/dict/header_footer_keywords_ja.txt
hojichar/dict/violence_keywords_ja.txt
hojichar/filters/__init__.py
hojichar/filters/deduplication.py
hojichar/filters/document_filters.py
hojichar/filters/language_identification.py
hojichar/filters/token_filters.py
hojichar/filters/tokenization.py
hojichar/utils/__init__.py
hojichar/utils/async_handlers.py
hojichar/utils/io_iter.py
hojichar/utils/load_compose.py
hojichar/utils/warn_deprecation.py
hojichar-0.16.0.dist-info/METADATA
hojichar-0.16.0.dist-info/WHEEL
hojichar-0.16.0.dist-info/entry_points.txt
hojichar-0.16.0.dist-info/licenses/LICENSE
hojichar-0.16.0.dist-info/RECORD
