Metadata-Version: 2.4
Name: hojichar
Version: 0.16.0
Summary: Text preprocessing management system.
Project-URL: Homepage, https://github.com/HojiChar/HojiChar
Project-URL: Repository, https://github.com/HojiChar/HojiChar
Author-email: "kenta.shinzato" <hoppiece@gmail.com>
License-Expression: Apache-2.0
License-File: LICENSE
Classifier: Operating System :: MacOS
Classifier: Operating System :: POSIX :: Linux
Classifier: Programming Language :: Python :: 3
Classifier: Programming Language :: Python :: 3.9
Classifier: Programming Language :: Python :: 3.10
Classifier: Programming Language :: Python :: 3.11
Classifier: Programming Language :: Python :: 3.12
Classifier: Programming Language :: Python :: 3.13
Requires-Python: <3.14,>=3.9
Requires-Dist: numpy<2.0,>=1.26; python_version >= '3.9'
Requires-Dist: tqdm<5,>=4.65.0
Provides-Extra: all
Requires-Dist: emoji<3,>=2.13.2; extra == 'all'
Requires-Dist: fasttext<0.10,>=0.9.3; extra == 'all'
Requires-Dist: fugashi[unidic-lite]<2,>=1.3.2; extra == 'all'
Requires-Dist: requests<3,>=2.32.3; extra == 'all'
Provides-Extra: dedup
Requires-Dist: datasketch>=1.6.5; extra == 'dedup'
Requires-Dist: fugashi>=1.5.1; extra == 'dedup'
Requires-Dist: nltk>=3.9.1; extra == 'dedup'
Requires-Dist: redis>=6.2.0; extra == 'dedup'
Requires-Dist: rensa>=0.2.7; extra == 'dedup'
Requires-Dist: xxhash>=3.5.0; extra == 'dedup'
Provides-Extra: openai
Requires-Dist: openai[aiohttp]>=1.89.0; extra == 'openai'
Requires-Dist: tenacity>=9.1.2; extra == 'openai'
